{
  "LastUpdatePro": "10:00 21/01/2024",
  "TvMarqueeEn": "📢 Please note. this app is a free app.  Can be used with unlimited bandwidth  Please follow the news here 24 hours a day.",
  "TvMarqueeMy": "📢 ကျေးဇူးပြု၍ ဤအက်ပ်သည် အခမဲ့အက်ပ်တစ်ခုဖြစ်သည်။  အကန့်အသတ်မရှိ bandwidth ဖြင့်အသုံးပြုနိုင်သည် ကျေးဇူးပြု၍ ဤနေရာတွင် 24 နာရီတစ်ရက်သတင်းကိုလိုက်နာပါ။",
  "TvMarqueeTh": "📢โปรดทราบ แอพนี้คือแอพฟรีน่ะครับ ใช้งานได้ไม่จำกัดแบนวิธ โปรดติดตามข่าวสารได้ที่นี่ 24 ชั่วโมง",
  "DtacMessageEn": "\u003cp\u003edtac recommends applying as follows\u003cbr\u003eUse the DTAC NOPRO channel.\u003cbr\u003e\u003cbr\u003edtac balance check code\u003cbr\u003e*101# Check Money Check Date \u003ca href\u003d\"tel:*101#\"\u003eclick\u003c/a\u003e\u003cbr\u003e*101*1# check balance \u003ca href\u003d\"tel:*101*1#\"\u003eclick\u003c/a\u003e\u003cbr\u003e*102# check number \u003ca href\u003d\"tel:*102#\"\u003eclick\u003c/a\u003e\u003cbr\u003e\u003cbr\u003eTrip: dtac internet activation code\u003cbr\u003eOpen dtac internet *104*71# call \u003ca href\u003d\"tel:*104*71#\"\u003eclick\u003c/a\u003e\u003cbr\u003eTurn off dtac internet *104*72# call \u003ca href\u003d\"tel:*104*72#\"\u003eclick\u003c/a\u003e\u003c/p\u003e\u003cp\u003eMethod 1 Apply for dtac to prevent money leakage.\u003cbr\u003edtac pro 64 kb 20 baht 30 days press *117*30# call \u003ca href\u003d\"tel:*117*30#\"\u003eclick\u003c/a\u003e\u003cbr\u003e\u003cbr\u003eNote: or do not need to apply at all. If there is no money in the sim For dtac sims who apply for a leak proof internet promotion But connected and the internet can test not more than 4 Mbps, apply for dtac pro Tamjai. Apply at dtac app\u003c/p\u003e\u003cp\u003eMethod 2 (Main Pro)\u003cbr\u003e\u003cbr\u003e1. Top up before 30 baht (if you have it, do not need to top up)\u003cbr\u003e2. Change the main promotion to Happy Call, dial *103*99#, apply for 30 baht. \u003ca href\u003d\"tel:*103*99#\"\u003eclick\u003c/a\u003e\u003cbr\u003e3. Top up a minimum of 50 baht to receive a 30-day anti-leakage promotion.\u003cbr\u003e\u003cbr\u003eNote: Must change the main promotion to Happy Call first only, top up 50 baht to get a leak-proof promotion Free.\u003c/p\u003e",
  "TrueMessageEn": "\u003cp\u003eTrue Move recommends applying as follows.\u003cbr\u003eUse the TRUE NOPRO channel.\u003cbr\u003e\u003cbr\u003eTrueMove balance check code\u003cbr\u003e*123# check money, check date \u003ca href\u003d\"tel:*123#\"\u003eclick\u003c/a\u003e\u003cbr\u003e*900# check balance \u003ca href\u003d\"tel:*900#\"\u003eclick\u003c/a\u003e\u003cbr\u003e*933# check number \u003ca href\u003d\"tel:*933#\"\u003eclick\u003c/a\u003e\u003cbr\u003e\u003cbr\u003eTrip: TrueMove internet activation code\u003cbr\u003eOpen True Move Internet *902*01# Call \u003ca href\u003d\"tel:*902*01#\"\u003eclick\u003c/a\u003e\u003cbr\u003eTurn off True Move internet *902*02# call \u003ca href\u003d\"tel:*902*02#\"\u003eclick\u003c/a\u003e\u003cbr\u003e\u003cbr\u003eApply for True Move Pro to prevent money leakage.\u003cbr\u003eTrue Move Pro 64 kb 32 baht 30 days\u003cbr\u003ePress *900*8131# call out \u003ca href\u003d\"tel:*900*8131#\"\u003eclick\u003c/a\u003e\u003cbr\u003e\u003cbr\u003eNote: or do not need to apply at all. If there is no money in the sim\u003c/p\u003e",
  "AisMessageEn": "\u003cp\u003eAIS is not yet recommended.\u003cbr\u003e\u003cbr\u003ebalance check code AIS\u003cbr\u003e*121# Check Money Check Date \u003ca href\u003d\"tel:*121#\"\u003eclick\u003c/a\u003e\u003cbr\u003e*121*32# เช็คยอดคงเหลือ \u003ca href\u003d\"tel:*121*32#\"\u003eclick\u003c/a\u003e\u003cbr\u003e*545# check number \u003ca href\u003d\"tel:*545#\"\u003eclick\u003c/a\u003e\u003cbr\u003e\u003cbr\u003eTrip: AIS internet on/off code\u003cbr\u003eOpen AIS internet *129*2# call \u003ca href\u003d\"tel:*129*2#\"\u003eclick\u003c/a\u003e\u003cbr\u003eTurn off AIS internet *129*1# call \u003ca href\u003d\"tel:*129*1#\"\u003eclick\u003c/a\u003e\u003cbr\u003e\u003cbr\u003eMethod 1\u003cbr\u003eCan only be used with 1Mb pro SIMs or higher.\u003cbr\u003ecan connect to increase internet speed \u003cbr\u003eIf there is no promotion, I do not recommend applying. because only some SIMs can be used\u003cbr\u003e\u003cbr\u003e\u003cbr\u003eMethod 2\u003cbr\u003e\u003cbr\u003eAIS Pro 128kb, internet leak protection, 33 baht, 30 days\u003cbr\u003ePress *777*7068*123456# \u003ca href\u003d\"tel:*777*7068*123456#\"\u003eclick\u003c/a\u003e\u003cbr\u003e\u003cbr\u003eApply for AISPLAY promotion 59 baht 1 month\u003cbr\u003ePress *777*885# call out \u003ca href\u003d\"tel:*777*885#\"\u003eclick\u003c/a\u003e\u003cbr\u003e\u003cbr\u003e\u003cbr\u003eNote: Apply for both promotions.\u003cbr\u003eIf you can try it, it won\u0027t hurt, only waste of money 😆\u003cbr\u003eBut admin doesn\u0027t recommend it.\u003c/p\u003e",
  "DtacMessageMy": "\u003cp\u003edtac မှ အောက်ပါအတိုင်း လျှောက်ထားရန် အကြံပြုအပ်ပါသည်။\u003cbr\u003eDTAC NOPRO ချန်နယ်ကို အသုံးပြုပါ။\u003cbr\u003e\u003cbr\u003edtac လက်ကျန်စစ်ဆေးကုဒ်\u003cbr\u003e*101# ငွေစစ်ဆေးသည့်ရက်စွဲ \u003ca href\u003d\"tel:*101#\"\u003eနှိပ်ပါ။\u003c/a\u003e\u003cbr\u003e*101*1# စစ်ဆေးရန် လက်ကျန် \u003ca href\u003d\"tel:*101*1#\"\u003eနှိပ်ပါ။\u003c/a\u003e\u003cbr\u003e*102# နံပါတ်စစ်ဆေးပါ။ \u003ca href\u003d\"tel:*102#\"\u003eနှိပ်ပါ။\u003c/a\u003e\u003cbr\u003e\u003cbr\u003eခရီးစဉ်- dtac အင်တာနက် စတင်ခြင်းကုဒ်\u003cbr\u003edtac အင်တာနက်ကို *104*71# သို့ ဖုန်းခေါ်ဆိုပါ။ \u003ca href\u003d\"tel:*104*71#\"\u003eနှိပ်ပါ။\u003c/a\u003e\u003cbr\u003edtac အင်တာနက် *104*72# ခေါ်ဆိုမှုကို ပိတ်ပါ။ \u003ca href\u003d\"tel:*104*72#\"\u003eနှိပ်ပါ။\u003c/a\u003e\u003c/p\u003e\u003cp\u003eနည်းလမ်း 1 ငွေယိုစိမ့်မှုကို ကာကွယ်ရန် dtac ကို လျှောက်ထားပါ။\u003cbr\u003edtac pro 64 kb 20 ဘတ် *117*30# ကိုနှိပ်ပြီး ရက် 30 ဖုန်းခေါ်ဆိုပါ။ \u003ca href\u003d\"tel:*117*30#\"\u003eနှိပ်ပါ။\u003c/a\u003e\u003cbr\u003e\u003cbr\u003eမှတ်ချက်- သို့မဟုတ် လုံးဝလျှောက်ထားရန် မလိုအပ်ပါ။ ပေါက်ကြားမှုအထောက်အထားအင်တာနက်ပရိုမိုးရှင်းအတွက်လျှောက်ထားသော dtac sim များအတွက် ငွေမရှိသော်လည်း ချိတ်ဆက်ပြီး 4 Mbps ထက်မပိုသော အင်တာနက်စမ်းသပ်နိုင်ပါက dtac pro Tamjai ကိုလျှောက်ထားပါ။ dtac အက်ပ်တွင် လျှောက်ထားပါ။\u003c/p\u003e\u003cp\u003eနည်းလမ်း 2 (Main Pro)\u003cbr\u003e\u003cbr\u003e1. ဘတ် 30 မတိုင်မီ ငွေဖြည့်သွင်းပါ (ရှိပါက ငွေဖြည့်ရန် မလိုအပ်ပါ)\u003cbr\u003e2. ပင်မပရိုမိုးရှင်းကို Happy Call သို့ပြောင်းပါ၊ *103*99# ကိုခေါ်ဆိုပါ၊ ဘတ် 30 လျှောက်ထားပါ။ \u003ca href\u003d\"tel:*103*99#\"\u003eနှိပ်ပါ။\u003c/a\u003e\u003cbr\u003e3. ရက် 30 ယိုစိမ့်မှုတိုက်ဖျက်ရေး ပရိုမိုးရှင်းတစ်ခုရရှိရန် အနည်းဆုံး 50 ဘတ်ငွေဖြည့်ပါ။\u003cbr\u003e\u003cbr\u003eမှတ်ချက်- ပင်မပရိုမိုးရှင်းကို Happy Call သို့ ဦးစွာပြောင်းရမည်ဖြစ်ပြီး ပေါက်ကြားမှုကင်းစင်သော ပရိုမိုးရှင်းတစ်ခု အခမဲ့ရရှိရန် ဘတ် 50 ဖြည့်သွင်းရပါမည်။\u003c/p\u003e",
  "TrueMessageMy": "\u003cp\u003eTrue Move က အောက်ပါအတိုင်း လျှောက်ထားရန် အကြံပြုထားသည်။\u003cbr\u003eTRUE NOPRO ချန်နယ်ကို အသုံးပြုပါ။\u003cbr\u003e\u003cbr\u003eTrueMove လက်ကျန်စစ်ချက်ကုဒ်\u003cbr\u003e*123# ငွေစစ်၊ စစ်ဆေးသည့်ရက်စွဲ \u003ca href\u003d\"tel:*123#\"\u003eနှိပ်ပါ။\u003c/a\u003e\u003cbr\u003e*900# check balance \u003ca href\u003d\"tel:*900#\"\u003eနှိပ်ပါ။\u003c/a\u003e\u003cbr\u003e*933# နံပါတ်စစ်ဆေးပါ။ \u003ca href\u003d\"tel:*933#\"\u003eနှိပ်ပါ။\u003c/a\u003e\u003cbr\u003e\u003cbr\u003eခရီးစဉ်- TrueMove အင်တာနက် စဖွင့်သုံးကုဒ်\u003cbr\u003eTrue Move အင်တာနက်ကိုဖွင့်ပြီး *902*01# ကိုခေါ်ဆိုပါ။ \u003ca href\u003d\"tel:*902*01#\"\u003eနှိပ်ပါ။\u003c/a\u003e\u003cbr\u003eTrue Move အင်တာနက် *902*02# ခေါ်ဆိုမှုကို ပိတ်ပါ။ \u003ca href\u003d\"tel:*902*02#\"\u003eနှိပ်ပါ။\u003c/a\u003e\u003cbr\u003e\u003cbr\u003eငွေယိုစိမ့်မှုကို ကာကွယ်ရန် True Move Pro ကို လျှောက်ထားပါ။\u003cbr\u003eTrue Move Pro 64 kb 32 ဘတ် 30 ရက်\u003cbr\u003e*900*8131# ကိုနှိပ်၍ ဖုန်းခေါ်ဆိုပါ။ \u003ca href\u003d\"tel:*900*8131#\"\u003eနှိပ်ပါ။\u003c/a\u003e\u003cbr\u003e\u003cbr\u003eမှတ်ချက်- သို့မဟုတ် လုံးဝလျှောက်ထားရန် မလိုအပ်ပါ။ Sim မှာ ပိုက်ဆံမရှိရင်\u003c/p\u003e",
  "AisMessageMy": "\u003cp\u003eAIS က မထောက်ခံသေးဘူး။\u003cbr\u003e\u003cbr\u003eလက်ကျန်စစ်ဆေးခြင်းကုဒ် AIS\u003cbr\u003e*121# ငွေစစ်ဆေးသည့်ရက်စွဲ \u003ca href\u003d\"tel:*121#\"\u003eနှိပ်ပါ။\u003c/a\u003e\u003cbr\u003e*121*32# စစ်ဆေးရန် လက်ကျန် \u003ca href\u003d\"tel:*121*32#\"\u003eနှိပ်ပါ။\u003c/a\u003e\u003cbr\u003e*545# နံပါတ်စစ်ဆေးပါ။ \u003ca href\u003d\"tel:*545#\"\u003eနှိပ်ပါ။\u003c/a\u003e\u003cbr\u003e\u003cbr\u003eခရီးစဉ်- AIS အင်တာနက် ဖွင့်/ပိတ် ကုဒ်\u003cbr\u003eAIS အင်တာနက်ကို *129*2# ခေါ်ဆို၍ ဖွင့်ပါ။ \u003ca href\u003d\"tel:*129*2#\"\u003eနှိပ်ပါ။\u003c/a\u003e\u003cbr\u003eAIS အင်တာနက် *129*1# ခေါ်ဆိုမှုကို ပိတ်ပါ။ \u003ca href\u003d\"tel:*129*1#\"\u003eနှိပ်ပါ။\u003c/a\u003e\u003cbr\u003e\u003cbr\u003eနည်းလမ်း ၁\u003cbr\u003e1Mb pro SIM နှင့် အထက်တွင်သာ အသုံးပြုနိုင်သည်။\u003cbr\u003eအင်တာနက် မြန်နှုန်းကို မြှင့်တင်ရန် ချိတ်ဆက်နိုင်သည်။ \u003cbr\u003eပရိုမိုးရှင်းမရှိရင် လျှောက်ထားဖို့ အကြံပြုလိုပါတယ်။ အဘယ်ကြောင့်ဆိုသော် အချို့သော SIM များကိုသာ အသုံးပြုနိုင်ပါသည်။\u003cbr\u003e\u003cbr\u003e\u003cbr\u003eနည်းလမ်း ၂\u003cbr\u003e\u003cbr\u003eAIS Pro 128kb၊ အင်တာနက်ယိုစိမ့်မှုကာကွယ်မှု၊ 33ဘတ်၊ ရက် 30\u003cbr\u003e*777*7068*123456# ကိုနှိပ်ပါ။ \u003ca href\u003d\"tel:*777*7068*123456#\"\u003eနှိပ်ပါ။\u003c/a\u003e\u003cbr\u003e\u003cbr\u003eAISPLAY ပရိုမိုးရှင်းအတွက် 59 ဘတ် 1 လ လျှောက်ထားပါ။\u003cbr\u003e*777*885# ကိုနှိပ်၍ ဖုန်းခေါ်ဆိုပါ။ \u003ca href\u003d\"tel:*777*885#\"\u003eနှိပ်ပါ။\u003c/a\u003e\u003cbr\u003e\u003cbr\u003e\u003cbr\u003eမှတ်ချက်- ပရိုမိုးရှင်းနှစ်ခုစလုံးအတွက် လျှောက်ထားပါ။\u003cbr\u003eစမ်းသုံးကြည့်​နိုင်​ရင်​ ​ငွေကုန်​​ငွေမကုန်​ဘူး 😆\u003cbr\u003eဒါပေမယ့် Admin က အကြံမပေးပါဘူး။\u003c/p\u003e",
  "DtacMessageTh": "\u003cp\u003eดีแทคแนะนำให้สมัครตามนี้\u003cbr\u003eใช้ช่อง DTAC NOPRO\u003cbr\u003e\u003cbr\u003eรหัสเช็คยอดดีแทค\u003cbr\u003e*101# เช็คเงิน เช็ควัน \u003ca href\u003d\"tel:*101#\"\u003eคลิ๊ก\u003c/a\u003e\u003cbr\u003e*101*1# เช็คยอดคงเหลือ \u003ca href\u003d\"tel:*101*1#\"\u003eคลิ๊ก\u003c/a\u003e\u003cbr\u003e*102# เช็คเบอร์ \u003ca href\u003d\"tel:*102#\"\u003eคลิ๊ก\u003c/a\u003e\u003cbr\u003e\u003cbr\u003eทริป: รหัสเปิดปิดเน็ตดีแทค\u003cbr\u003eเปิดเน็ตดีแทค *104*71# โทรออก \u003ca href\u003d\"tel:*104*71#\"\u003eคลิ๊ก\u003c/a\u003e\u003cbr\u003eปิดเน็ตดีแทค *104*72# โทรออก \u003ca href\u003d\"tel:*104*72#\"\u003eคลิ๊ก\u003c/a\u003e\u003c/p\u003e\u003cp\u003eวิธีที่ 1 สมัครดีแทคโปรป้องกันเงินรั่ว\u003cbr\u003eดีแทคโปร 64 kb 20 บาท 30 วัน กด *117*30# โทรออก \u003ca href\u003d\"tel:*117*30#\"\u003eคลิ๊ก\u003c/a\u003e\u003cbr\u003e\u003cbr\u003eหมายเหตุ: หรือไม่ต้องสมัครอะไรเลยก็ใด้ ถ้าไม่มีเงินในซิม สำหรับซิมดีแทคใครที่สมัครโปรเน็ตกันรั่ว แต่เชื่อมต่อแล้วอินเทอร์เน็ตทดสอบได้ไม่เกิน 4 Mbps ให้ไปสมัครดีแทคโปรตามใจเสริมเข้าไป สมัครได้ที่แอพดีแทค\u003c/p\u003e\u003cp\u003eวิธีที่ 2 (โปรหลัก)\u003cbr\u003e\u003cbr\u003e1. เติมเงินก่อน 30 บาท (ถ้ามีแล้วไม่ต้องเติม)\u003cbr\u003e2. เปลียนโปรหลักเป็นแฮปปี้คอล กด *103*99# สมัคร 30 บาท \u003ca href\u003d\"tel:*103*99#\"\u003eคลิ๊ก\u003c/a\u003e\u003cbr\u003e3. เติมเงินขั้นต่ำ 50บาท เพื่อรับสิทธิ์โปรกั้นรั่วใช้งาน 30วัน\u003cbr\u003e\u003cbr\u003eหมายเหตุ : ต้องเปลียนโปรหลักเป็นแฮปปี้คอลก่อนเท่านั้น เติมเงิน 50บาท ถึ่งจะได้โปรกั้นรั่ว\u003c/p\u003e",
  "TrueMessageTh": "\u003cp\u003eทรูมูฟแนะนำให้สมัครตามนี้\u003cbr\u003eใช้ช่อง TRUE NOPRO\u003cbr\u003e\u003cbr\u003eรหัสเช็คยอดทรูมูฟ\u003cbr\u003e*123# เช็คเงิน เช็ควัน \u003ca href\u003d\"tel:*123#\"\u003eคลิ๊ก\u003c/a\u003e\u003cbr\u003e*900# เช็คยอดคงเหลือ \u003ca href\u003d\"tel:*900#\"\u003eคลิ๊ก\u003c/a\u003e\u003cbr\u003e*933# เช็คเบอร์ \u003ca href\u003d\"tel:*933#\"\u003eคลิ๊ก\u003c/a\u003e\u003cbr\u003e\u003cbr\u003eทริป: รหัสเปิดปิดเน็ตทรูมูฟ\u003cbr\u003eเปิดเน็ตทรูมูฟ *902*01# โทรออก \u003ca href\u003d\"tel:*902*01#\"\u003eคลิ๊ก\u003c/a\u003e\u003cbr\u003eปิดเน็ตทรูมูฟ *902*02# โทรออก \u003ca href\u003d\"tel:*902*02#\"\u003eคลิ๊ก\u003c/a\u003e\u003cbr\u003e\u003cbr\u003eสมัครทรูมูฟโปรป้องกันเงินรั่ว\u003cbr\u003eทรูมูฟโปร 64 kb 32 บาท 30 วัน\u003cbr\u003eกด *900*8131# โทรออก \u003ca href\u003d\"tel:*900*8131#\"\u003eคลิ๊ก\u003c/a\u003e\u003cbr\u003e\u003cbr\u003eหมายเหตุ: หรือไม่ต้องสมัครอะไรเลยก็ใด้ ถ้าไม่มีเงินในซิม\u003c/p\u003e",
  "AisMessageTh": "\u003cp\u003eเอไอเอส ยังไม่แนะนำให้ใช้\u003cbr\u003e\u003cbr\u003eรหัสเช็คยอด AIS\u003cbr\u003e*121# เช็คเงิน เช็ควัน \u003ca href\u003d\"tel:*121#\"\u003eคลิ๊ก\u003c/a\u003e\u003cbr\u003e*121*32# เช็คยอดคงเหลือ \u003ca href\u003d\"tel:*121*32#\"\u003eคลิ๊ก\u003c/a\u003e\u003cbr\u003e*545# เช็คเบอร์ \u003ca href\u003d\"tel:*545#\"\u003eคลิ๊ก\u003c/a\u003e\u003cbr\u003e\u003cbr\u003eทริป: รหัสเปิดปิดเน็ตเอไอเอส\u003cbr\u003eเปิดเน็ตเอไอเอส *129*2# โทรออก \u003ca href\u003d\"tel:*129*2#\"\u003eคลิ๊ก\u003c/a\u003e\u003cbr\u003eปิดเน็ตเอไอเอส *129*1# โทรออก \u003ca href\u003d\"tel:*129*1#\"\u003eคลิ๊ก\u003c/a\u003e\u003cbr\u003e\u003cbr\u003eวิธีที่ 1\u003cbr\u003eใช้ได้เฉพาะซิมที่มีโปร 1Mb หรือแรงกว่านั้น\u003cbr\u003eสามารถเชื่อมต่อเพื่อเพิ่มความเร็วอินเทอร์เน็ต \u003cbr\u003eถ้าไม่มีโปรไม่แนะนำให้สมัคร เพราะใช้งานได้แค่บางซิม\u003cbr\u003e\u003cbr\u003e\u003cbr\u003eวิธีที่ 2\u003cbr\u003eAIS โปร128kb กันเน็ตรั่ว 33 บาท 30 วัน\u003cbr\u003eกด *777*7068*123456# \u003ca href\u003d\"tel:*777*7068*123456#\"\u003eคลิ๊ก\u003c/a\u003e\u003cbr\u003e\u003cbr\u003eสมัคร โปร AISPLAY 59 บาท 1เดือน\u003cbr\u003eกด *777*885# โทรออก \u003ca href\u003d\"tel:*777*885#\"\u003eคลิ๊ก\u003c/a\u003e\u003cbr\u003e\u003cbr\u003eหมายเหตุ:สมัครทั้ง 2 โปร\u003cbr\u003eถ้าจะลองดูก็ได้ไม่เสียหาย เสียแต่เงิน😆\u003cbr\u003eแต่แอดมินไม่แนะนำ\u003c/p\u003e"
}
